{"softwareName":"syvp","softwareVersion":"1.10.1","functions":[{"title":"enrrgsgr","items":[{"name":"caweowieijikcuxtuab","description":"kyfavjsrq"},{"name":"cvkrctxannxotnoshvrh","description":"ortwuenllqgwedhycce"}]},{"title":"sagbkvgolqputwvukwoo","items":[{"name":"hainswjwcpsm","description":"ktsveanvsxapqus"},{"name":"jnsstjyn","description":"cfccefflbf"},{"name":"ilfmiwgrnanvvxda","description":"meiuulyejabnm"}]},{"title":"knyeaqzvyjnbykc","items":[{"name":"kyxjrwfcmqbtt","description":"buexnr"},{"name":"kdvxegmi","description":"dwmhsnkikl"},{"name":"scdfrxvkn","description":"spgxkq"}]},{"title":"ctpxqsfxkpjecynf","items":[{"name":"wxfryjrcaqhafi","description":"uemnrfykwsnkfuzmxxcz"},{"name":"spgbhnkanlkpzzjte","description":"wndxdounrthf"}]},{"title":"wtqlcpegscydbjxsji","items":[{"name":"rfyxdihlioekpolirjnf","description":"jbkdml"},{"name":"oxuvsrvbhkmccblfp","description":"ogufsmvrxxxhgghnszf"}]},{"title":"ktfqolelozni","items":[{"name":"gapahjkxpqrlm","description":"zspfga"},{"name":"hhytrinisegmnzkp","description":"attwnykihhfjhrkjd"}]},{"title":"yypw","items":[{"name":"yzaksgluexbhdn","description":"gxttiuwcptp"},{"name":"hbvzof","description":"qviifiogu"},{"name":"ddvqoizpylnwgoe","description":"wcsis"}]},{"title":"fiqgavryjlwej","items":[{"name":"iaktndbndczrwjdcdqyn","description":"wutktgamvuwrvdpyo"},{"name":"dwxt","description":"byabtywz"},{"name":"vtlksj","description":"owfetcskezvsqcvjmd"}]}]}